[
	{
		"pkg": "@capacitor/app",
		"classpath": "com.capacitorjs.plugins.app.AppPlugin"
	},
	{
		"pkg": "@capacitor/local-notifications",
		"classpath": "com.capacitorjs.plugins.localnotifications.LocalNotificationsPlugin"
	},
	{
		"pkg": "@capacitor/status-bar",
		"classpath": "com.capacitorjs.plugins.statusbar.StatusBarPlugin"
	},
	{
		"pkg": "@capacitor/storage",
		"classpath": "com.capacitorjs.plugins.storage.StoragePlugin"
	},
	{
		"pkg": "@robingenz/capacitor-android-dark-mode-support",
		"classpath": "dev.robingenz.capacitor.androiddarkmodesupport.AndroidDarkModeSupportPlugin"
	},
	{
		"pkg": "capacitor-plugin-safe-area",
		"classpath": "com.zhuxian.safearea.SafeAreaPlugin"
	},
	{
		"pkg": "capacitor-secure-storage-plugin",
		"classpath": "com.whitestein.securestorage.SecureStoragePlugin"
	}
]
